geoprepare/__init__.py
geoprepare/base.py
geoprepare/geobase.txt
geoprepare/geodownload.py
geoprepare/geoextract.py
geoprepare/geoextract.txt
geoprepare/geoextract_bangladesh.txt
geoprepare/geomerge.py
geoprepare/log.py
geoprepare/utils.py
geoprepare/datasets/AVHRR.py
geoprepare/datasets/AgERA5.py
geoprepare/datasets/CHIRPS.py
geoprepare/datasets/CHIRPS_GEFS.py
geoprepare/datasets/CPC.py
geoprepare/datasets/ESI.py
geoprepare/datasets/FLDAS.py
geoprepare/datasets/FPAR.py
geoprepare/datasets/GLDAS.py
geoprepare/datasets/LST.py
geoprepare/datasets/NDVI.py
geoprepare/datasets/NSIDC.py
geoprepare/datasets/Soil_Moisture.py
geoprepare/datasets/VHI.py
geoprepare/datasets/__init__.py
geoprepare/datasets/template.nc
geoprepare/datasets/template.tif
geoprepare/diagnostics/__init__.py
geoprepare/diagnostics/count_files.py
geoprepare/docs/links.md
geoprepare/docs/run.md
geoprepare/eoaccess/__init__.py
geoprepare/eoaccess/eo2.py
geoprepare/eoaccess/eoaccess.py
geoprepare/eoaccess/tmp.py
geoprepare/extract/__init__.py
geoprepare/extract/extract_EO.py
geoprepare/extract/stats.py
geoprepare/extract/util/raster/__init__.py
geoprepare/extract/util/raster/array.py
geoprepare/extract/util/raster/raster.py
geoprepare/merge/__init__.py
geoprepare/playground/combine.py
geoprepare/playground/config_extract_ewcm.py
geoprepare/playground/stats.py
geoprepare/playground/tmp.py
geoprepare-0.6.24.dist-info/licenses/LICENSE
geoprepare-0.6.24.dist-info/METADATA
geoprepare-0.6.24.dist-info/WHEEL
geoprepare-0.6.24.dist-info/top_level.txt
geoprepare-0.6.24.dist-info/RECORD
