Metadata-Version: 2.4
Name: geoprepare
Version: 0.6.24
Summary: A Python package to prepare (download, extract, process input data) for GEOCIF and related models
Author-email: Ritvik Sahajpal <ritvik@umd.edu>
License: MIT
Project-URL: Homepage, https://github.com/ritviksahajpal/geoprepare
Project-URL: Documentation, https://ritviksahajpal.github.io/geoprepare
Project-URL: Repository, https://github.com/ritviksahajpal/geoprepare
Project-URL: Issues, https://github.com/ritviksahajpal/geoprepare/issues
Keywords: geoprepare,geospatial,agriculture,remote-sensing,earth-observation
Classifier: Development Status :: 2 - Pre-Alpha
Classifier: Intended Audience :: Developers
Classifier: Intended Audience :: Science/Research
Classifier: License :: OSI Approved :: MIT License
Classifier: Natural Language :: English
Classifier: Operating System :: OS Independent
Classifier: Programming Language :: Python :: 3
Classifier: Programming Language :: Python :: 3.9
Classifier: Programming Language :: Python :: 3.10
Classifier: Programming Language :: Python :: 3.11
Classifier: Programming Language :: Python :: 3.12
Classifier: Topic :: Scientific/Engineering :: GIS
Requires-Python: >=3.9
License-File: LICENSE
Provides-Extra: dev
Requires-Dist: bump2version; extra == "dev"
Requires-Dist: wheel; extra == "dev"
Requires-Dist: watchdog; extra == "dev"
Requires-Dist: flake8; extra == "dev"
Requires-Dist: tox; extra == "dev"
Requires-Dist: coverage; extra == "dev"
Requires-Dist: Sphinx; extra == "dev"
Requires-Dist: twine; extra == "dev"
Requires-Dist: grip; extra == "dev"
Requires-Dist: pytest; extra == "dev"
Requires-Dist: pytest-cov; extra == "dev"
Requires-Dist: black; extra == "dev"
Requires-Dist: isort; extra == "dev"
Requires-Dist: mypy; extra == "dev"
Provides-Extra: docs
Requires-Dist: mkdocs; extra == "docs"
Requires-Dist: mkdocstrings; extra == "docs"
Requires-Dist: mkdocs-material; extra == "docs"
Requires-Dist: mkdocs-jupyter; extra == "docs"
Requires-Dist: mkdocs-git-revision-date-plugin; extra == "docs"
Dynamic: license-file
